{
  "mode": "pre",
  "tag": "next",
  "initialVersions": {
    "@twind/core": "1.0.0-next.0",
    "@twind/preset-autoprefix": "1.0.0-next.0",
    "@twind/preset-mini": "1.0.0-next.0",
    "@twind/preset-tailwind": "1.0.0-next.0",
    "twind": "1.0.0-next.0",
    "@twind/runtime": "1.0.0-next.5"
  },
  "changesets": [
    "afraid-donuts-teach",
    "angry-trees-scream",
    "clean-apples-clean",
    "cyan-mayflies-fix",
    "eleven-papayas-run",
    "hot-flowers-smile",
    "kind-fireants-shop",
    "lemon-cherries-know",
    "light-spies-bathe",
    "neat-teachers-repeat",
    "new-olives-complain",
    "odd-needles-carry",
    "pink-rockets-look",
    "popular-flowers-grin",
    "proud-jobs-train",
    "selfish-schools-perform",
    "sixty-pugs-cheer",
    "smart-balloons-tease",
    "spicy-boats-applaud",
    "spotty-badgers-tan",
    "stupid-bottles-heal",
    "tricky-hotels-move",
    "tricky-sloths-build",
    "twelve-shirts-pretend",
    "unlucky-pants-press",
    "weak-otters-sort",
    "wild-rats-flash"
  ]
}
